{"cameraMode":{"drawMode":0,"name":"Shaded","section":"Shading Mode"},"sceneLighting":true,"audioPlay":false,"sceneViewState":{"m_AlwaysRefresh":false,"showFog":true,"showSkybox":true,"showFlares":true,"showImageEffects":true,"showParticleSystems":true,"showVisualEffectGraphs":true,"m_FxEnabled":true},"in2DMode":false,"pivot":{"x":-1.3910613059997559,"y":-0.9999990463256836,"z":-4.552764415740967},"rotation":{"x":-0.08112375438213349,"y":0.8349074125289917,"z":-0.12797921895980836,"w":-0.5291406512260437},"size":1.001873254776001,"orthographic":false}